MagicAI/__init__.py
MagicAI/assistant.py
MagicAI/output_parser.py
MagicAI/prompt.py
MagicAI/time_monitor.py
MagicAI/token_count_handler.py
MagicAI/tool_call_handler.py
MagicAI/tool_manager.py
magicsoft_ai-0.1.1.dist-info/licenses/LICENSE
magicsoft_ai-0.1.1.dist-info/METADATA
magicsoft_ai-0.1.1.dist-info/WHEEL
magicsoft_ai-0.1.1.dist-info/top_level.txt
magicsoft_ai-0.1.1.dist-info/RECORD
