Metadata-Version: 2.4
Name: magicsoft-ai
Version: 0.1.1
Summary: A module for AI assistant functionalities (version 1)
Author-email: Sreedev Melethil <sreedev.melethil@magic-hire.com>
Project-URL: Homepage, https://github.com/Magic-Hire/Yukthi-ai-agent-package/
Classifier: Programming Language :: Python :: 3
Classifier: Operating System :: OS Independent
Classifier: Development Status :: 3 - Alpha
Classifier: Intended Audience :: Developers
Requires-Python: >=3.10
License-File: LICENSE
Requires-Dist: langchain>=0.3.23
Requires-Dist: langchain-community>=0.3.21
Requires-Dist: langchain-google-genai>=2.0.1
Requires-Dist: langchain-deepseek>=0.1.2
Requires-Dist: loguru>=0.7.0
Dynamic: license-file
